{
    "text": "\n\n",
    "socialLinks": [],
    "legalLinks": [],
    "copyrightText": "<div style=\"text-align: center\">`São Paulo / Mogi das Cruzes (SP) - 11 986195444 -` <engenharia@utop.com.br> `- © 2024 UTOP Engenharia`</div>\n\n",
    "colors": "bg-light-fg-dark",
    "type": "Footer",
    "title": "",
    "styles": {
        "self": {
            "padding": [
                "pt-0",
                "pl-0"
            ],
            "margin": [
                "ml-0",
                "mt-0"
            ]
        }
    }
}